<annotation>
  <folder>DATASET</folder>
  <filename>10125.jpg</filename>
  <source>
    <database>FaceDataset</database>
  </source>
  <size>
    <width>612</width>
    <height>408</height>
    <depth>3</depth>
  </size>
  <segmented>0</segmented>
  <object>
    <name>f</name>
    <pose>Unspecified</pose>
    <truncated>0</truncated>
    <difficult>0</difficult>
    <bndbox>
      <xmin>385</xmin>
      <ymin>114</ymin>
      <xmax>496</xmax>
      <ymax>225</ymax>
    </bndbox>
  </object>
  <object>
    <name>f</name>
    <pose>Unspecified</pose>
    <truncated>0</truncated>
    <difficult>0</difficult>
    <bndbox>
      <xmin>317</xmin>
      <ymin>113</ymin>
      <xmax>364</xmax>
      <ymax>159</ymax>
    </bndbox>
  </object>
  <object>
    <name>f</name>
    <pose>Unspecified</pose>
    <truncated>0</truncated>
    <difficult>0</difficult>
    <bndbox>
      <xmin>248</xmin>
      <ymin>110</ymin>
      <xmax>286</xmax>
      <ymax>148</ymax>
    </bndbox>
  </object>
</annotation>
