<annotation>
  <folder>DATASET</folder>
  <filename>10399.jpg</filename>
  <source>
    <database>FaceDataset</database>
  </source>
  <size>
    <width>612</width>
    <height>408</height>
    <depth>3</depth>
  </size>
  <segmented>0</segmented>
  <object>
    <name>f</name>
    <pose>Unspecified</pose>
    <truncated>0</truncated>
    <difficult>0</difficult>
    <bndbox>
      <xmin>210</xmin>
      <ymin>39</ymin>
      <xmax>390</xmax>
      <ymax>131</ymax>
    </bndbox>
  </object>
  <object>
    <name>f</name>
    <pose>Unspecified</pose>
    <truncated>0</truncated>
    <difficult>0</difficult>
    <bndbox>
      <xmin>56</xmin>
      <ymin>173</ymin>
      <xmax>309</xmax>
      <ymax>306</ymax>
    </bndbox>
  </object>
</annotation>
