<annotation>
  <folder>DATASET</folder>
  <filename>11045.jpg</filename>
  <source>
    <database>FaceDataset</database>
  </source>
  <size>
    <width>612</width>
    <height>408</height>
    <depth>3</depth>
  </size>
  <segmented>0</segmented>
  <object>
    <name>f</name>
    <pose>Unspecified</pose>
    <truncated>0</truncated>
    <difficult>0</difficult>
    <bndbox>
      <xmin>289</xmin>
      <ymin>170</ymin>
      <xmax>340</xmax>
      <ymax>221</ymax>
    </bndbox>
  </object>
  <object>
    <name>f</name>
    <pose>Unspecified</pose>
    <truncated>0</truncated>
    <difficult>0</difficult>
    <bndbox>
      <xmin>288</xmin>
      <ymin>108</ymin>
      <xmax>352</xmax>
      <ymax>146</ymax>
    </bndbox>
  </object>
  <object>
    <name>f</name>
    <pose>Unspecified</pose>
    <truncated>0</truncated>
    <difficult>0</difficult>
    <bndbox>
      <xmin>182</xmin>
      <ymin>145</ymin>
      <xmax>244</xmax>
      <ymax>195</ymax>
    </bndbox>
  </object>
  <object>
    <name>f</name>
    <pose>Unspecified</pose>
    <truncated>0</truncated>
    <difficult>0</difficult>
    <bndbox>
      <xmin>244</xmin>
      <ymin>123</ymin>
      <xmax>290</xmax>
      <ymax>180</ymax>
    </bndbox>
  </object>
  <object>
    <name>f</name>
    <pose>Unspecified</pose>
    <truncated>0</truncated>
    <difficult>0</difficult>
    <bndbox>
      <xmin>323</xmin>
      <ymin>145</ymin>
      <xmax>388</xmax>
      <ymax>182</ymax>
    </bndbox>
  </object>
</annotation>
