<annotation>
  <folder>DATASET</folder>
  <filename>11073.jpg</filename>
  <source>
    <database>FaceDataset</database>
  </source>
  <size>
    <width>612</width>
    <height>408</height>
    <depth>3</depth>
  </size>
  <segmented>0</segmented>
  <object>
    <name>f</name>
    <pose>Unspecified</pose>
    <truncated>0</truncated>
    <difficult>0</difficult>
    <bndbox>
      <xmin>280</xmin>
      <ymin>96</ymin>
      <xmax>399</xmax>
      <ymax>203</ymax>
    </bndbox>
  </object>
  <object>
    <name>f</name>
    <pose>Unspecified</pose>
    <truncated>0</truncated>
    <difficult>0</difficult>
    <bndbox>
      <xmin>98</xmin>
      <ymin>30</ymin>
      <xmax>232</xmax>
      <ymax>162</ymax>
    </bndbox>
  </object>
</annotation>
