<annotation>
  <folder>DATASET</folder>
  <filename>13411.jpg</filename>
  <source>
    <database>FaceDataset</database>
  </source>
  <size>
    <width>612</width>
    <height>408</height>
    <depth>3</depth>
  </size>
  <segmented>0</segmented>
  <object>
    <name>f</name>
    <pose>Unspecified</pose>
    <truncated>0</truncated>
    <difficult>0</difficult>
    <bndbox>
      <xmin>188</xmin>
      <ymin>143</ymin>
      <xmax>268</xmax>
      <ymax>220</ymax>
    </bndbox>
  </object>
  <object>
    <name>f</name>
    <pose>Unspecified</pose>
    <truncated>0</truncated>
    <difficult>0</difficult>
    <bndbox>
      <xmin>494</xmin>
      <ymin>207</ymin>
      <xmax>540</xmax>
      <ymax>247</ymax>
    </bndbox>
  </object>
  <object>
    <name>f</name>
    <pose>Unspecified</pose>
    <truncated>0</truncated>
    <difficult>0</difficult>
    <bndbox>
      <xmin>556</xmin>
      <ymin>165</ymin>
      <xmax>583</xmax>
      <ymax>188</ymax>
    </bndbox>
  </object>
  <object>
    <name>f</name>
    <pose>Unspecified</pose>
    <truncated>0</truncated>
    <difficult>0</difficult>
    <bndbox>
      <xmin>79</xmin>
      <ymin>78</ymin>
      <xmax>148</xmax>
      <ymax>139</ymax>
    </bndbox>
  </object>
  <object>
    <name>f</name>
    <pose>Unspecified</pose>
    <truncated>0</truncated>
    <difficult>0</difficult>
    <bndbox>
      <xmin>303</xmin>
      <ymin>123</ymin>
      <xmax>394</xmax>
      <ymax>208</ymax>
    </bndbox>
  </object>
  <object>
    <name>f</name>
    <pose>Unspecified</pose>
    <truncated>0</truncated>
    <difficult>0</difficult>
    <bndbox>
      <xmin>446</xmin>
      <ymin>169</ymin>
      <xmax>479</xmax>
      <ymax>197</ymax>
    </bndbox>
  </object>
  <object>
    <name>f</name>
    <pose>Unspecified</pose>
    <truncated>0</truncated>
    <difficult>0</difficult>
    <bndbox>
      <xmin>270</xmin>
      <ymin>137</ymin>
      <xmax>316</xmax>
      <ymax>178</ymax>
    </bndbox>
  </object>
</annotation>
