<annotation>
  <folder>DATASET</folder>
  <filename>14189.jpg</filename>
  <source>
    <database>FaceDataset</database>
  </source>
  <size>
    <width>612</width>
    <height>408</height>
    <depth>3</depth>
  </size>
  <segmented>0</segmented>
  <object>
    <name>f</name>
    <pose>Unspecified</pose>
    <truncated>0</truncated>
    <difficult>0</difficult>
    <bndbox>
      <xmin>227</xmin>
      <ymin>133</ymin>
      <xmax>282</xmax>
      <ymax>217</ymax>
    </bndbox>
  </object>
  <object>
    <name>f</name>
    <pose>Unspecified</pose>
    <truncated>0</truncated>
    <difficult>0</difficult>
    <bndbox>
      <xmin>483</xmin>
      <ymin>67</ymin>
      <xmax>520</xmax>
      <ymax>108</ymax>
    </bndbox>
  </object>
  <object>
    <name>f</name>
    <pose>Unspecified</pose>
    <truncated>0</truncated>
    <difficult>0</difficult>
    <bndbox>
      <xmin>460</xmin>
      <ymin>116</ymin>
      <xmax>490</xmax>
      <ymax>155</ymax>
    </bndbox>
  </object>
  <object>
    <name>f</name>
    <pose>Unspecified</pose>
    <truncated>0</truncated>
    <difficult>0</difficult>
    <bndbox>
      <xmin>566</xmin>
      <ymin>61</ymin>
      <xmax>597</xmax>
      <ymax>97</ymax>
    </bndbox>
  </object>
</annotation>
